__init__.py
adlike/__init__.py
adlike/adlike.py
adlike-0.0.5.dist-info/METADATA
adlike-0.0.5.dist-info/WHEEL
adlike-0.0.5.dist-info/top_level.txt
adlike-0.0.5.dist-info/RECORD
