Metadata-Version: 2.1
Name: adlike
Version: 0.0.5
Summary: A python package to determine if an Image is an Advertisement
Author-email: Chitra Vyanjan <chitra.vyanjan@gmail.com>
Project-URL: Homepage, https://github.com/chitradrishti/adlike
Project-URL: Issues, https://github.com/chitradrishti/adlike/issues
Classifier: Programming Language :: Python :: 3
Classifier: License :: OSI Approved :: MIT License
Classifier: Operating System :: OS Independent
Requires-Python: >=3.8
